basetrig/__init__.py
basetrig/trig.py
basetrig-0.0.1.dist-info/METADATA
basetrig-0.0.1.dist-info/WHEEL
basetrig-0.0.1.dist-info/top_level.txt
basetrig-0.0.1.dist-info/RECORD
