Metadata-Version: 2.1
Name: basetrig
Version: 0.0.1
Summary: Basic operations on trigonometric functions
Home-page: https://github.com/cjenf/trigfunc
Author: Cheng
Author-email: cjenf844747@gmail.com
License: MIT license
Requires-Python: >=3.11.4
